{"cameraMode":{"drawMode":0,"name":"Shaded","section":"Shading Mode"},"sceneLighting":true,"audioPlay":false,"sceneViewState":{"m_AlwaysRefresh":false,"showFog":true,"showSkybox":true,"showFlares":true,"showImageEffects":true,"showParticleSystems":true,"showVisualEffectGraphs":true,"m_FxEnabled":true},"in2DMode":false,"pivot":{"x":339.9898986816406,"y":-410.03607177734377,"z":998.254150390625},"rotation":{"x":0.2909260392189026,"y":0.09131200611591339,"z":-0.026162339374423028,"w":0.9524016976356506},"size":915.6046142578125,"orthographic":false}